LICENSE
MANIFEST.in
README.md
lab_black.py
nb_black.py
setup.cfg
setup.py
nb_black_only.egg-info/PKG-INFO
nb_black_only.egg-info/SOURCES.txt
nb_black_only.egg-info/dependency_links.txt
nb_black_only.egg-info/not-zip-safe
nb_black_only.egg-info/requires.txt
nb_black_only.egg-info/top_level.txt