Metadata-Version: 2.1
Name: nb-black-only
Version: 1.0.9
Summary: A simple extension for Jupyter Notebook and Jupyter Lab to beautify Python code automatically using Black. This version only supports black and stripts yapf support. Based on https://github.com/dnanhkhoa/nb_black
Home-page: https://github.com/Rjdrenth/nb_black_only
Author: Khoa Duong
Author-email: dnanhkhoa@live.com
License: MIT
Keywords: black-formatter black-beautifier black jupyterlab-extension jupyter-notebook-extension
Platform: UNKNOWN
Classifier: Development Status :: 5 - Production/Stable
Classifier: Intended Audience :: Developers
Classifier: License :: OSI Approved :: MIT License
Classifier: Programming Language :: Python
Classifier: Programming Language :: Python :: 2
Classifier: Programming Language :: Python :: 3
Classifier: Topic :: Software Development :: Libraries :: Python Modules
